{
  "HTML1": {
    "_id": "ecc4294",
    "extra": {
      "nota": 11
    },
    "prompts": [
      {
        "q": "cell:nota",
        "a": "exato+extra"
      }
    ]
  },
  "HTML2": {
    "_id": "ecc4294",
    "extra": {
      "nota": 10
    },
    "prompts": [
      {
        "q": "cell:nota",
        "a": "exato"
      }
    ]
  },
  "CSS1": {
    "_id": "ecc4294",
    "extra": {
      "nota": 10
    },
    "prompts": [
      {
        "q": "cell:nota",
        "a": "exato"
      }
    ]
  },
  "CSS2": {
    "_id": "ecc4294",
    "extra": {
      "nota": 10
    },
    "prompts": [
      {
        "q": "cell:nota",
        "a": "exato"
      }
    ]
  },
  "CSS3": {
    "_id": "ecc4294",
    "extra": {
      "nota": 10
    },
    "prompts": [
      {
        "q": "cell:nota",
        "a": "exato"
      }
    ]
  },
  "JS1": {
    "_id": "63fb10a",
    "extra": {
      "nota": 10
    },
    "prompts": [
      {
        "q": "cell:nota",
        "a": "exato"
      }
    ]
  },
  "JS2": {
    "_id": "ecc4294",
    "extra": {
      "nota": 10
    },
    "prompts": [
      {
        "q": "cell:nota",
        "a": "exato"
      }
    ]
  },
  "JS3": {
    "_id": "f222288",
    "extra": {
      "nota": 0
    },
    "prompts": [
      {
        "q": "cell:nota",
        "a": "inválido"
      }
    ]
  },
  "JS4": {
    "_id": "f222288",
    "extra": {
      "nota": 0
    },
    "prompts": [
      {
        "q": "cell:nota",
        "a": "inválido"
      }
    ]
  }
}